LICENSE.txt
MANIFEST.in
README.md
setup.py
documentation/index.rst
documentation/install.rst
documentation/keyboard.rst
documentation/mouse.rst
documentation/msgbox.rst
documentation/quickstart.rst
documentation/roadmap.rst
documentation/tests.rst
uiaction/__init__.py
uiaction/__main__.py
uiaction/_uiaction_java.py
uiaction/_uiaction_osx.py
uiaction/_uiaction_win.py
uiaction/_uiaction_x11.py
uiaction.egg-info/PKG-INFO
uiaction.egg-info/SOURCES.txt
uiaction.egg-info/dependency_links.txt
uiaction.egg-info/requires.txt
uiaction.egg-info/top_level.txt