Metadata-Version: 2.1
Name: uiaction
Version: 0.9.53
Summary: uiaction lets Python control the mouse and keyboard, and other GUI automation tasks. For Windows, macOS, and Linux, on Python 3 and 2.
Home-page: https://github.com/SriBalajiSMVEC/uiaction
Author: BalajiSanthanam
Author-email: sribalaji2112@gmail.com
License: MIT
Keywords: gui automation test testing keyboard mouse cursor click press keystroke control
Platform: UNKNOWN
Classifier: Development Status :: 4 - Beta
Classifier: Environment :: Win32 (MS Windows)
Classifier: Environment :: X11 Applications
Classifier: Environment :: MacOS X
Classifier: Intended Audience :: Developers
Classifier: License :: OSI Approved :: MIT License
Classifier: Operating System :: OS Independent
Classifier: Programming Language :: Python
Classifier: Programming Language :: Python :: 2
Classifier: Programming Language :: Python :: 2.7
Classifier: Programming Language :: Python :: 3
Classifier: Programming Language :: Python :: 3.1
Classifier: Programming Language :: Python :: 3.2
Classifier: Programming Language :: Python :: 3.3
Classifier: Programming Language :: Python :: 3.4
Classifier: Programming Language :: Python :: 3.5
Classifier: Programming Language :: Python :: 3.6
Classifier: Programming Language :: Python :: 3.7
Classifier: Programming Language :: Python :: 3.8
License-File: LICENSE.txt
